shellerate/__init__.py
shellerate/asm_x86.py
shellerate/egg_hunter.py
shellerate/encoder.py
shellerate/math.py
shellerate/not_encoder.py
shellerate/strings.py
shellerate/xority.py
shellerate-0.4.3.data/scripts/shellerate
shellerate-0.4.3.dist-info/LICENSE
shellerate-0.4.3.dist-info/METADATA
shellerate-0.4.3.dist-info/WHEEL
shellerate-0.4.3.dist-info/top_level.txt
shellerate-0.4.3.dist-info/RECORD
