Metadata-Version: 2.1
Name: shellerate
Version: 0.4.3
Summary: A shellcode generator with encryption, encoding and polymorphism facilities built-in
Home-page: https://github.com/thesp0nge/shellerate
Author: Paolo Perego
Author-email: paolo@codiceinsicuro.it
License: UNKNOWN
Platform: UNKNOWN
Classifier: Programming Language :: Python :: 3
Classifier: License :: OSI Approved :: MIT License
Classifier: Operating System :: OS Independent
Requires-Python: >=3.6.*
License-File: LICENSE
